cramjam-2.9.0.dist-info/METADATA
cramjam-2.9.0.dist-info/WHEEL
cramjam-2.9.0.dist-info/licenses/LICENSE
cramjam/__init__.py
cramjam/cramjam.pypy310-pp73-x86_64-linux-gnu.so
cramjam-2.9.0.dist-info/RECORD
