Metadata-Version: 2.3
Name: cramjam
Version: 2.9.0
Requires-Dist: black ==22.3.0 ; extra == 'dev'
Requires-Dist: numpy ; extra == 'dev'
Requires-Dist: pytest >=5.30 ; extra == 'dev'
Requires-Dist: pytest-xdist ; extra == 'dev'
Requires-Dist: pytest-benchmark ; extra == 'dev'
Requires-Dist: hypothesis ; extra == 'dev'
Provides-Extra: dev
License-File: LICENSE
Summary: Thin Python bindings to de/compression algorithms in Rust
Keywords: compression,decompression,snappy,zstd,bz2,gzip,lz4,brotli,deflate,blosc2
Author: Miles Granger <miles59923@gmail.com>
Author-email: Miles Granger <miles59923@gmail.com>
License: MIT
Requires-Python: >=3.8
Project-URL: homepage, https://github.com/milesgranger/pyrus-cramjam
Project-URL: documentation, https://docs.rs/cramjam/latest/cramjam
Project-URL: repository, https://github.com/milesgranger/pyrus-cramjam
